license.txt.txt
setup.py
distributions/Binomialdistribution.py
distributions/Gaussiandistribution.py
distributions/Generaldistribution.py
distributions/__init__.py
prob_dist_12345.egg-info/PKG-INFO
prob_dist_12345.egg-info/SOURCES.txt
prob_dist_12345.egg-info/dependency_links.txt
prob_dist_12345.egg-info/not-zip-safe
prob_dist_12345.egg-info/top_level.txt